rabbitleap/__init__.py
rabbitleap/__version__.py
rabbitleap/consumer.py
rabbitleap/envelope.py
rabbitleap/exceptions.py
rabbitleap/handling.py
rabbitleap/retry_policies.py
rabbitleap/routing.py
rabbitleap-0.1.1.dist-info/LICENSE.txt
rabbitleap-0.1.1.dist-info/METADATA
rabbitleap-0.1.1.dist-info/RECORD
rabbitleap-0.1.1.dist-info/WHEEL
rabbitleap-0.1.1.dist-info/top_level.txt
